jenkinstools/__init__.py
jenkinstools/jenkins_auth.py
jenkinstools/jenkins_show.py
jenkinstools/jenkinsclient.py
jenkinstools/jenkinstools.py
goatjenkinstools-2024.7.16.1622.dist-info/METADATA
goatjenkinstools-2024.7.16.1622.dist-info/WHEEL
goatjenkinstools-2024.7.16.1622.dist-info/entry_points.txt
goatjenkinstools-2024.7.16.1622.dist-info/top_level.txt
goatjenkinstools-2024.7.16.1622.dist-info/RECORD
