Metadata-Version: 2.1
Name: goatjenkinstools
Version: 2024.7.16.1622
Summary: jenkinstools - everything you need to interact with Jenkins
Author-email: Chris Stacks <centerupt@gmail.com>
Classifier: Programming Language :: Python :: 3
Classifier: Operating System :: OS Independent
Requires-Python: >=3.7
Requires-Dist: python-jenkins
Requires-Dist: click >=8.0.4
Requires-Dist: six
